[
  {
    "colander_type": "ALERT",
    "misp_object": "colander-event",
    "misp_definition": "",
    "misp_colander_mapping": {
      "discriminator": {
        "type": "match",
        "property": "event_type",
        "target": "attribute-value",
        "value": "Alert"
      }
    },
    "colander_misp_mapping": {
      "literals": {
        "event_type": "Alert"
      },
      "misp_attributes": {
        "name": "name",
        "description": "description",
        "count": "count",
        "first_seen": "first_seen",
        "last_seen": "last_seen"
      }
    }
  },
  {
    "colander_type": "ATTACK",
    "misp_object": "colander-event",
    "misp_definition": "",
    "misp_colander_mapping": {
      "discriminator": {
        "type": "match",
        "property": "event_type",
        "target": "attribute-value",
        "value": "Attack"
      }
    },
    "colander_misp_mapping": {
      "literals": {
        "event_type": "Attack"
      },
      "misp_attributes": {
        "name": "name",
        "description": "description",
        "count": "count",
        "first_seen": "first_seen",
        "last_seen": "last_seen"
      }
    }
  },
  {
    "colander_type": "TARGETED_ATTACK",
    "misp_object": "colander-event",
    "misp_definition": "",
    "misp_colander_mapping": {
      "discriminator": {
        "type": "match",
        "property": "event_type",
        "target": "attribute-value",
        "value": "Targeted attack"
      }
    },
    "colander_misp_mapping": {
      "literals": {
        "event_type": "Targeted attack"
      },
      "misp_attributes": {
        "name": "name",
        "description": "description",
        "count": "count",
        "first_seen": "first_seen",
        "last_seen": "last_seen"
      }
    }
  },
  {
    "colander_type": "AV_DETECTION",
    "misp_object": "colander-event",
    "misp_definition": "",
    "misp_colander_mapping": {
      "discriminator": {
        "type": "match",
        "property": "event_type",
        "target": "attribute-value",
        "value": "Antivirus detection"
      }
    },
    "colander_misp_mapping": {
      "literals": {
        "event_type": "Antivirus detection"
      },
      "misp_attributes": {
        "name": "name",
        "description": "description",
        "count": "count",
        "first_seen": "first_seen",
        "last_seen": "last_seen"
      }
    }
  },
  {
    "colander_type": "COMMUNICATION",
    "misp_object": "colander-event",
    "misp_definition": "",
    "misp_colander_mapping": {
      "discriminator": {
        "type": "match",
        "property": "event_type",
        "target": "attribute-value",
        "value": "Communication"
      }
    },
    "colander_misp_mapping": {
      "literals": {
        "event_type": "Communication"
      },
      "misp_attributes": {
        "name": "name",
        "description": "description",
        "count": "count",
        "first_seen": "first_seen",
        "last_seen": "last_seen"
      }
    }
  },
  {
    "colander_type": "COMPROMISE",
    "misp_object": "colander-event",
    "misp_definition": "",
    "misp_colander_mapping": {
      "discriminator": {
        "type": "match",
        "property": "event_type",
        "target": "attribute-value",
        "value": "Compromise"
      }
    },
    "colander_misp_mapping": {
      "literals": {
        "event_type": "Compromise"
      },
      "misp_attributes": {
        "name": "name",
        "description": "description",
        "count": "count",
        "first_seen": "first_seen",
        "last_seen": "last_seen"
      }
    }
  },
  {
    "colander_type": "GENERIC",
    "misp_object": "colander-event",
    "misp_definition": "",
    "misp_colander_mapping": {
      "discriminator": {
        "type": "match",
        "property": "event_type",
        "target": "attribute-value",
        "value": "Generic"
      }
    },
    "colander_misp_mapping": {
      "literals": {
        "event_type": "Generic"
      },
      "misp_attributes": {
        "name": "name",
        "description": "description",
        "count": "count",
        "first_seen": "first_seen",
        "last_seen": "last_seen"
      }
    }
  },
  {
    "colander_type": "HIT",
    "misp_object": "colander-event",
    "misp_definition": "",
    "misp_colander_mapping": {
      "discriminator": {
        "type": "match",
        "property": "event_type",
        "target": "attribute-value",
        "value": "Hit"
      }
    },
    "colander_misp_mapping": {
      "literals": {
        "event_type": "Hit"
      },
      "misp_attributes": {
        "name": "name",
        "description": "description",
        "count": "count",
        "first_seen": "first_seen",
        "last_seen": "last_seen"
      }
    }
  },
  {
    "colander_type": "INFECTION",
    "misp_object": "colander-event",
    "misp_definition": "",
    "misp_colander_mapping": {
      "discriminator": {
        "type": "match",
        "property": "event_type",
        "target": "attribute-value",
        "value": "Infection"
      }
    },
    "colander_misp_mapping": {
      "literals": {
        "event_type": "Infection"
      },
      "misp_attributes": {
        "name": "name",
        "description": "description",
        "count": "count",
        "first_seen": "first_seen",
        "last_seen": "last_seen"
      }
    }
  },
  {
    "colander_type": "PASSIVE_DNS",
    "misp_object": "colander-event",
    "misp_definition": "",
    "misp_colander_mapping": {
      "discriminator": {
        "type": "match",
        "property": "event_type",
        "target": "attribute-value",
        "value": "Passive DNS"
      }
    },
    "colander_misp_mapping": {
      "literals": {
        "event_type": "Passive DNS"
      },
      "misp_attributes": {
        "name": "name",
        "description": "description",
        "count": "count",
        "first_seen": "first_seen",
        "last_seen": "last_seen"
      }
    }
  },
  {
    "colander_type": "RESOLVE",
    "misp_object": "colander-event",
    "misp_definition": "",
    "misp_colander_mapping": {
      "discriminator": {
        "type": "match",
        "property": "event_type",
        "target": "attribute-value",
        "value": "Resolve"
      }
    },
    "colander_misp_mapping": {
      "literals": {
        "event_type": "Resolve"
      },
      "misp_attributes": {
        "name": "name",
        "description": "description",
        "count": "count",
        "first_seen": "first_seen",
        "last_seen": "last_seen"
      }
    }
  }
]
