{
  "component": {
    "name": "ButterKnife Project",
    "version": "unknown",
    "category": "imported",
    "platforms": [
      "all"
    ],
    "languages": [
      "unknown"
    ],
    "description": "Signatures for ButterKnife Project - JakeWharton",
    "license": "Apache-2.0",
    "publisher": "JakeWharton"
  },
  "signature_metadata": {
    "version": "1.0.0",
    "created": "2025-08-04T15:40:01.450691Z",
    "updated": "2025-08-05T00:00:00Z",
    "signature_count": 0,
    "confidence_threshold": 0.7,
    "source": "converted_from_bsa_format",
    "original_file": "jakewharton-butterknife.json",
    "cleaned": true,
    "cleaning_version": "2.0"
  },
  "signatures": []
}