{
  "component": {
    "name": "FasterXML Jackson",
    "version": "unknown",
    "category": "data-processing",
    "platforms": [
      "java"
    ],
    "languages": [
      "java"
    ],
    "description": "Signatures for FasterXML Jackson - FasterXML",
    "license": "Apache-2.0",
    "publisher": "FasterXML"
  },
  "signature_metadata": {
    "version": "1.0.0",
    "created": "2025-08-04T15:40:01.390615Z",
    "updated": "2025-08-05T00:00:00Z",
    "signature_count": 0,
    "confidence_threshold": 0.7,
    "source": "converted_from_bsa_format",
    "original_file": "fasterxml-jackson.json",
    "cleaned": true,
    "cleaning_version": "2.0"
  },
  "signatures": []
}