{
  "component": {
    "name": "Qt5 Framework",
    "version": "5.12.8",
    "category": "imported",
    "platforms": [
      "all"
    ],
    "languages": [
      "native"
    ],
    "description": "Qt5 cross-platform application framework",
    "license": "LGPL-3.0",
    "publisher": "The Qt Company"
  },
  "signature_metadata": {
    "version": "1.0.0",
    "created": "2025-08-06T00:47:35.607747Z",
    "updated": "2025-08-06T00:47:35.607764Z",
    "signature_count": 13,
    "confidence_threshold": 0.7,
    "source": "binary_analysis",
    "extraction_method": "symbol_extraction",
    "cleaned": true,
    "cleaning_version": "2.0"
  },
  "signatures": [
    {
      "id": "qt5_framework_7",
      "type": "prefix_pattern",
      "pattern": "Key_Dead_",
      "confidence": 0.85,
      "context": "binary_symbol",
      "platforms": [
        "all"
      ]
    },
    {
      "id": "qt5_framework_28",
      "type": "string_pattern",
      "pattern": "QProcess::",
      "confidence": 0.9,
      "context": "binary_symbol",
      "platforms": [
        "all"
      ]
    },
    {
      "id": "qt5_framework_30",
      "type": "string_pattern",
      "pattern": "Qt 5.12.8 (x86_64-little_endian-llp64 shared (dynamic) release build; by MSVC 2017)",
      "confidence": 0.9,
      "context": "binary_symbol",
      "platforms": [
        "all"
      ]
    },
    {
      "id": "qt5_framework_52",
      "type": "prefix_pattern",
      "pattern": "QWidget::",
      "confidence": 0.95,
      "context": "binary_symbol",
      "platforms": [
        "all"
      ]
    },
    {
      "id": "qt5_framework_53",
      "type": "prefix_pattern",
      "pattern": "QApplication::",
      "confidence": 0.95,
      "context": "binary_symbol",
      "platforms": [
        "all"
      ]
    },
    {
      "id": "qt5_framework_79",
      "type": "string_pattern",
      "pattern": "QSharedMemory::",
      "confidence": 0.9,
      "context": "binary_symbol",
      "platforms": [
        "all"
      ]
    },
    {
      "id": "qt5_framework_82",
      "type": "prefix_pattern",
      "pattern": "QObject::",
      "confidence": 0.95,
      "context": "binary_symbol",
      "platforms": [
        "all"
      ]
    },
    {
      "id": "qt5_framework_83",
      "type": "string_pattern",
      "pattern": "QMetaObject::",
      "confidence": 0.95,
      "context": "binary_symbol",
      "platforms": [
        "all"
      ]
    },
    {
      "id": "qt5_framework_84",
      "type": "prefix_pattern",
      "pattern": "QString::",
      "confidence": 0.95,
      "context": "binary_symbol",
      "platforms": [
        "all"
      ]
    },
    {
      "id": "qt5_framework_85",
      "type": "string_pattern",
      "pattern": "QVariant::",
      "confidence": 0.95,
      "context": "binary_symbol",
      "platforms": [
        "all"
      ]
    },
    {
      "id": "qt5_framework_97",
      "type": "prefix_pattern",
      "pattern": "QThread::",
      "confidence": 0.95,
      "context": "binary_symbol",
      "platforms": [
        "all"
      ]
    },
    {
      "id": "qt5_framework_98",
      "type": "string_pattern",
      "pattern": "QCoreApplication::",
      "confidence": 0.95,
      "context": "binary_symbol",
      "platforms": [
        "all"
      ]
    },
    {
      "id": "qt5_framework_100",
      "type": "string_pattern",
      "pattern": "QAbstractAnimation::",
      "confidence": 0.9,
      "context": "binary_symbol",
      "platforms": [
        "all"
      ]
    }
  ]
}